the_pytech_calculator/__init__.py
the_pytech_calculator/add.py
the_pytech_calculator/divide.py
the_pytech_calculator/multiply.py
the_pytech_calculator/subtract.py
the_pytech_calculator/extras/__init__.py
the_pytech_calculator/extras/hello_world.py
the_pytech_calculator-0.0.2.dist-info/LICENSE
the_pytech_calculator-0.0.2.dist-info/METADATA
the_pytech_calculator-0.0.2.dist-info/WHEEL
the_pytech_calculator-0.0.2.dist-info/top_level.txt
the_pytech_calculator-0.0.2.dist-info/RECORD
