Metadata-Version: 2.1
Name: the_pytech_calculator
Version: 0.0.2
Summary: The first package for PyTech
Home-page: UNKNOWN
Author: Mason Mapfundematsva
Author-email: masonmapfunde@gmail.com
License: UNKNOWN
Keywords: python,calculator,math
Platform: UNKNOWN
Classifier: Development Status :: 1 - Planning
Classifier: Intended Audience :: Education
Classifier: License :: OSI Approved :: GNU General Public License v3 (GPLv3)
Classifier: Programming Language :: Python :: 3
Classifier: Operating System :: POSIX :: Linux
Classifier: Operating System :: MacOS :: MacOS X
Classifier: Operating System :: Microsoft :: Windows
License-File: LICENSE
